fastapi_cachex/__init__.py
fastapi_cachex/backends/__init__.py
fastapi_cachex/backends/base.py
fastapi_cachex/backends/config.py
fastapi_cachex/backends/memcached.py
fastapi_cachex/backends/memory.py
fastapi_cachex/backends/redis.py
fastapi_cachex/cache.py
fastapi_cachex/dependencies.py
fastapi_cachex/directives.py
fastapi_cachex/exceptions.py
fastapi_cachex/proxy.py
fastapi_cachex/py.typed
fastapi_cachex/routes.py
fastapi_cachex/session/__init__.py
fastapi_cachex/session/config.py
fastapi_cachex/session/dependencies.py
fastapi_cachex/session/exceptions.py
fastapi_cachex/session/manager.py
fastapi_cachex/session/middleware.py
fastapi_cachex/session/models.py
fastapi_cachex/session/proxy.py
fastapi_cachex/session/security.py
fastapi_cachex/session/token_serializers.py
fastapi_cachex/state/__init__.py
fastapi_cachex/state/exceptions.py
fastapi_cachex/state/manager.py
fastapi_cachex/state/models.py
fastapi_cachex/types.py
fastapi_cachex-0.2.10.dist-info/WHEEL
fastapi_cachex-0.2.10.dist-info/METADATA
fastapi_cachex-0.2.10.dist-info/RECORD
