Metadata-Version: 2.4
Name: fastapi-cachex
Version: 0.2.10
Summary: A caching library for FastAPI with support for Cache-Control, ETag, and multiple backends.
Keywords: fastapi,cache,etag,cache-control,redis,memcached,in-memory
Author: allen0099
Author-email: allen0099 <s96016641@gmail.com>
License-Expression: Apache-2.0
Classifier: Development Status :: 3 - Alpha
Classifier: Intended Audience :: Developers
Classifier: Programming Language :: Python
Classifier: Programming Language :: Python :: 3
Classifier: Programming Language :: Python :: 3.10
Classifier: Programming Language :: Python :: 3.11
Classifier: Programming Language :: Python :: 3.12
Classifier: Programming Language :: Python :: 3.13
Classifier: Programming Language :: Python :: 3.14
Classifier: Programming Language :: Python :: 3 :: Only
Classifier: Framework :: FastAPI
Classifier: Topic :: Software Development :: Libraries :: Python Modules
Classifier: Topic :: Internet :: WWW/HTTP :: HTTP Servers
Requires-Dist: fastapi
Requires-Dist: pydantic
Requires-Dist: pyjwt>=2.9.0 ; extra == 'jwt'
Requires-Dist: pymemcache ; extra == 'memcache'
Requires-Dist: redis[hiredis] ; extra == 'redis'
Requires-Dist: orjson ; extra == 'redis'
Requires-Python: >=3.10
Project-URL: Homepage, https://github.com/allen0099/FastAPI-CacheX
Project-URL: Repository, https://github.com/allen0099/FastAPI-CacheX.git
Project-URL: Issues, https://github.com/allen0099/FastAPI-CacheX/issues
Provides-Extra: jwt
Provides-Extra: memcache
Provides-Extra: redis
